PyQt5/Qt5/qsci/api/python/PyQtNetworkAuth.api
PyQt5/QtNetworkAuth.pyd
PyQt5/QtNetworkAuth.pyi
PyQt5/bindings/QtNetworkAuth/QtNetworkAuth.toml
PyQt5/bindings/QtNetworkAuth/QtNetworkAuthmod.sip
PyQt5/bindings/QtNetworkAuth/qabstractoauth.sip
PyQt5/bindings/QtNetworkAuth/qabstractoauth2.sip
PyQt5/bindings/QtNetworkAuth/qabstractoauthreplyhandler.sip
PyQt5/bindings/QtNetworkAuth/qoauth1.sip
PyQt5/bindings/QtNetworkAuth/qoauth1signature.sip
PyQt5/bindings/QtNetworkAuth/qoauth2authorizationcodeflow.sip
PyQt5/bindings/QtNetworkAuth/qoauthhttpserverreplyhandler.sip
PyQt5/bindings/QtNetworkAuth/qoauthoobreplyhandler.sip
PyQtNetworkAuth-5.15.6.dist-info/WHEEL
PyQtNetworkAuth-5.15.6.dist-info/METADATA
PyQtNetworkAuth-5.15.6.dist-info/RECORD
